drf_nested_creator/__init__.py
drf_nested_creator/creators.py
drf_nested_creator/fields.py
drf_nested_creator/serializers.py
src/__init__.py
src/creators.py
src/fields.py
src/serializers.py
drf_nested_creator-0.3.0.dist-info/LICENSE
drf_nested_creator-0.3.0.dist-info/METADATA
drf_nested_creator-0.3.0.dist-info/WHEEL
drf_nested_creator-0.3.0.dist-info/top_level.txt
drf_nested_creator-0.3.0.dist-info/RECORD
